expedia_travel_recommendations/__init__.py
expedia_travel_recommendations/main.py
expedia_travel_recommendations/api/__init__.py
expedia_travel_recommendations/api/client.py
expedia_travel_recommendations/api/handlers.py
expedia_travel_recommendations_mcp-1.0.2.dist-info/licenses/LICENSE
expedia_travel_recommendations_mcp-1.0.2.dist-info/METADATA
expedia_travel_recommendations_mcp-1.0.2.dist-info/WHEEL
expedia_travel_recommendations_mcp-1.0.2.dist-info/entry_points.txt
expedia_travel_recommendations_mcp-1.0.2.dist-info/top_level.txt
expedia_travel_recommendations_mcp-1.0.2.dist-info/RECORD
