Metadata-Version: 2.4
Name: expedia-travel-recommendations-mcp
Version: 1.0.2
Summary: Travel recommendations MCP Server
License:                                  Apache License
Requires-Python: >=3.11
License-File: LICENSE
Requires-Dist: fastmcp==2.5.1
Requires-Dist: mcp[cli]==1.9.1
Requires-Dist: python-dotenv>=1.1.0
Requires-Dist: requests==2.32.4
Dynamic: license-file
